kalayil.py
kalayil-0.1.4.dist-info/AUTHORS.txt
kalayil-0.1.4.dist-info/LICENSE.txt
kalayil-0.1.4.dist-info/METADATA
kalayil-0.1.4.dist-info/WHEEL
kalayil-0.1.4.dist-info/top_level.txt
kalayil-0.1.4.dist-info/RECORD
