Metadata-Version: 2.1
Name: kalayil
Version: 0.1.4
Summary: Package for easier Machine Learning Workflow.
Home-page: https://github.com/santokalayil/kalayil
Author: Santo K Thomas
Author-email: santokalayil@gmail.com
License: UNKNOWN
Platform: UNKNOWN
Classifier: License :: OSI Approved :: MIT License
Classifier: Programming Language :: Python :: 3
Classifier: Programming Language :: Python :: 3.7
Classifier: Programming Language :: Python :: 3.8
Classifier: Operating System :: OS Independent
